radar_chart/__init__.py
radar_chart/radar_chart.py
radar_chart-0.0.5.dist-info/LICENSE
radar_chart-0.0.5.dist-info/METADATA
radar_chart-0.0.5.dist-info/WHEEL
radar_chart-0.0.5.dist-info/top_level.txt
radar_chart-0.0.5.dist-info/RECORD
