Metadata-Version: 2.1
Name: radar-chart
Version: 0.0.5
Summary: A package to quickly visualise radar charts
Home-page: https://github.com/awaiskhan0/radar_chart
Author: Awais Khan
Author-email: awaisgithub@gmail.com
License: UNKNOWN
Platform: UNKNOWN
Classifier: Programming Language :: Python :: 3
Classifier: License :: OSI Approved :: MIT License
Classifier: Operating System :: OS Independent
Requires-Python: >=3.7
